{
  "info": {
    "description": "PlantDoc dataset",
    "version": "1.0",
    "year": 2020,
    "contributor": "PlantDoc",
    "source": "original",
    "license": {
      "name": "CC BY 4.0",
      "url": "https://creativecommons.org/licenses/by/4.0/"
    }
  },
  "images": [
    {
      "id": 8279684567,
      "width": 4272,
      "height": 2848,
      "file_name": "apple-tree-branch-plant-fruit-leaf-flower-food-green-produce-flora-immature-apple-tree-flowering-plant-wild-apple-tree-apple-gear-land-plant-606389.jpg",
      "size": 1979508,
      "format": "JPG",
      "url": "",
      "hash": "",
      "status": "success"
    }
  ],
  "annotations": [
    {
      "id": 0,
      "image_id": 8279684567,
      "category_id": 2,
      "bbox": [
        1651.0,
        24.0,
        2603.0,
        948.0
      ],
      "area": 2467644.0,
      "iscrowd": 0
    }
  ],
  "categories": [
    {
      "id": 2,
      "name": "apple_leaf",
      "supercategory": "apple_leaf"
    }
  ]
}