{
  "info": {
    "description": "PlantDoc dataset",
    "version": "1.0",
    "year": 2020,
    "contributor": "PlantDoc",
    "source": "original",
    "license": {
      "name": "CC BY 4.0",
      "url": "https://creativecommons.org/licenses/by/4.0/"
    }
  },
  "images": [
    {
      "id": 8139194953,
      "width": 660,
      "height": 276,
      "file_name": "Corn-gray-leaf-spot-8-15-F1-660.jpg",
      "size": 228137,
      "format": "JPG",
      "url": "",
      "hash": "",
      "status": "success"
    }
  ],
  "annotations": [
    {
      "id": 0,
      "image_id": 8139194953,
      "category_id": 8,
      "bbox": [
        1.0,
        35.0,
        659.0,
        234.0
      ],
      "area": 154206.0,
      "iscrowd": 0
    }
  ],
  "categories": [
    {
      "id": 8,
      "name": "corn_gray_leaf_spot",
      "supercategory": "corn_gray_leaf_spot"
    }
  ]
}