{
  "info": {
    "description": "PlantDoc dataset",
    "version": "1.0",
    "year": 2020,
    "contributor": "PlantDoc",
    "source": "original",
    "license": {
      "name": "CC BY 4.0",
      "url": "https://creativecommons.org/licenses/by/4.0/"
    }
  },
  "images": [
    {
      "id": 7846489553,
      "width": 1024,
      "height": 1024,
      "file_name": "depositphotos_3786198-Peach-leaf.jpg",
      "size": 64784,
      "format": "JPG",
      "url": "",
      "hash": "",
      "status": "success"
    }
  ],
  "annotations": [
    {
      "id": 0,
      "image_id": 7846489553,
      "category_id": 11,
      "bbox": [
        372.0,
        9.0,
        273.0,
        1015.0
      ],
      "area": 277095.0,
      "iscrowd": 0
    }
  ],
  "categories": [
    {
      "id": 11,
      "name": "peach_leaf",
      "supercategory": "peach_leaf"
    }
  ]
}