{
  "info": {
    "description": "PlantDoc dataset",
    "version": "1.0",
    "year": 2020,
    "contributor": "PlantDoc",
    "source": "original",
    "license": {
      "name": "CC BY 4.0",
      "url": "https://creativecommons.org/licenses/by/4.0/"
    }
  },
  "images": [
    {
      "id": 5878797279,
      "width": 1200,
      "height": 1507,
      "file_name": "late_blight_tomato_transplant2x1200.jpg",
      "size": 388674,
      "format": "JPG",
      "url": "",
      "hash": "",
      "status": "success"
    }
  ],
  "annotations": [
    {
      "id": 0,
      "image_id": 5878797279,
      "category_id": 23,
      "bbox": [
        165.0,
        133.0,
        794.0,
        1282.0
      ],
      "area": 1017908.0,
      "iscrowd": 0
    }
  ],
  "categories": [
    {
      "id": 23,
      "name": "tomato_leaf_late_blight",
      "supercategory": "tomato_leaf_late_blight"
    }
  ]
}