{
  "info": {
    "description": "PlantDoc dataset",
    "version": "1.0",
    "year": 2020,
    "contributor": "PlantDoc",
    "source": "original",
    "license": {
      "name": "CC BY 4.0",
      "url": "https://creativecommons.org/licenses/by/4.0/"
    }
  },
  "images": [
    {
      "id": 7663413130,
      "width": 1024,
      "height": 400,
      "file_name": "Northern-leaf-blight-in-corn.jpg",
      "size": 138552,
      "format": "JPG",
      "url": "",
      "hash": "",
      "status": "success"
    }
  ],
  "annotations": [
    {
      "id": 0,
      "image_id": 7663413130,
      "category_id": 9,
      "bbox": [
        77.0,
        1.0,
        722.0,
        399.0
      ],
      "area": 288078.0,
      "iscrowd": 0
    }
  ],
  "categories": [
    {
      "id": 9,
      "name": "corn_leaf_blight",
      "supercategory": "corn_leaf_blight"
    }
  ]
}