{
  "info": {
    "description": "PlantDoc dataset",
    "version": "1.0",
    "year": 2020,
    "contributor": "PlantDoc",
    "source": "original",
    "license": {
      "name": "CC BY 4.0",
      "url": "https://creativecommons.org/licenses/by/4.0/"
    }
  },
  "images": [
    {
      "id": 1118698249,
      "width": 566,
      "height": 566,
      "file_name": "Potato-blight-on-leaf.jpg",
      "size": 125815,
      "format": "JPG",
      "url": "",
      "hash": "",
      "status": "success"
    }
  ],
  "annotations": [
    {
      "id": 0,
      "image_id": 1118698249,
      "category_id": 13,
      "bbox": [
        29.0,
        101.0,
        519.0,
        347.0
      ],
      "area": 180093.0,
      "iscrowd": 0
    }
  ],
  "categories": [
    {
      "id": 13,
      "name": "potato_leaf_early_blight",
      "supercategory": "potato_leaf_early_blight"
    }
  ]
}